{
  "main": {
    "id": "6167823454d7d2e2",
    "type": "split",
    "children": [
      {
        "id": "b5c107453b88ba76",
        "type": "tabs",
        "children": [
          {
            "id": "b85724ed619ccd59",
            "type": "leaf",
            "state": {
              "type": "markdown",
              "state": {
                "file": "What is Computer Vision?.md",
                "mode": "source",
                "source": false
              }
            }
          }
        ]
      }
    ],
    "direction": "vertical"
  },
  "left": {
    "id": "f272f7c16045df9a",
    "type": "split",
    "children": [
      {
        "id": "39138105aea8f00d",
        "type": "tabs",
        "children": [
          {
            "id": "3535c8e000adf057",
            "type": "leaf",
            "state": {
              "type": "file-explorer",
              "state": {
                "sortOrder": "alphabetical"
              }
            }
          },
          {
            "id": "6657f4eecd6aaaaa",
            "type": "leaf",
            "state": {
              "type": "search",
              "state": {
                "query": "",
                "matchingCase": false,
                "explainSearch": false,
                "collapseAll": false,
                "extraContext": false,
                "sortOrder": "alphabetical"
              }
            }
          },
          {
            "id": "5e29e39fafc09f28",
            "type": "leaf",
            "state": {
              "type": "bookmarks",
              "state": {}
            }
          }
        ]
      }
    ],
    "direction": "horizontal",
    "width": 300
  },
  "right": {
    "id": "dbdb0088fb6d8b06",
    "type": "split",
    "children": [
      {
        "id": "f2bff6233576845e",
        "type": "tabs",
        "children": [
          {
            "id": "feafbb1fecba1e47",
            "type": "leaf",
            "state": {
              "type": "backlink",
              "state": {
                "file": "What is Computer Vision?.md",
                "collapseAll": false,
                "extraContext": false,
                "sortOrder": "alphabetical",
                "showSearch": false,
                "searchQuery": "",
                "backlinkCollapsed": false,
                "unlinkedCollapsed": true
              }
            }
          },
          {
            "id": "c1f3263b6e80f518",
            "type": "leaf",
            "state": {
              "type": "outgoing-link",
              "state": {
                "file": "What is Computer Vision?.md",
                "linksCollapsed": false,
                "unlinkedCollapsed": true
              }
            }
          },
          {
            "id": "2fd87dca284e88c6",
            "type": "leaf",
            "state": {
              "type": "tag",
              "state": {
                "sortOrder": "frequency",
                "useHierarchy": true
              }
            }
          },
          {
            "id": "ceb5516baeee6431",
            "type": "leaf",
            "state": {
              "type": "outline",
              "state": {
                "file": "What is Computer Vision?.md"
              }
            }
          }
        ]
      }
    ],
    "direction": "horizontal",
    "width": 300,
    "collapsed": true
  },
  "left-ribbon": {
    "hiddenItems": {
      "switcher:Open quick switcher": false,
      "graph:Open graph view": false,
      "canvas:Create new canvas": false,
      "daily-notes:Open today's daily note": false,
      "templates:Insert template": false,
      "command-palette:Open command palette": false
    }
  },
  "active": "b85724ed619ccd59",
  "lastOpenFiles": [
    "Tasks.md",
    "Untitled.md",
    "Project Roadmap.md",
    "Object Detection Project.md",
    "Presentation Plan.md",
    "What is Computer Vision?.md",
    "Task Table.md",
    "Team Directory.md",
    "Evaluation Steps.md"
  ]
}